clue_mq/__init__.py
clue_mq/exchange.py
clue_mq/worker.py
clue_mq-0.1.2.dist-info/METADATA
clue_mq-0.1.2.dist-info/WHEEL
clue_mq-0.1.2.dist-info/top_level.txt
clue_mq-0.1.2.dist-info/RECORD
