Metadata-Version: 2.1
Name: clue-mq
Version: 0.1.2
Summary: Message Queue Tools for python project
Home-page: https://github.com/linewalks/CLUE-MQ
Author: Linewalks
Author-email: jindex2411@linewalks.com
License: Linewalks
Platform: UNKNOWN
Requires-Python: >=3.6
Requires-Dist: kombu
